mail_alias_creator/__init__.py
mail_alias_creator/entry_processors/__init__.py
mail_alias_creator/entry_processors/base.py
mail_alias_creator/entry_processors/external_address.py
mail_alias_creator/entry_processors/group.py
mail_alias_creator/entry_processors/include_alias.py
mail_alias_creator/entry_processors/user.py
mail_alias_creator/interface.py
mail_alias_creator/ldap.py
mail_alias_creator/main.py
mail_alias_creator/process.py
mail_alias_creator-1.2.2.dist-info/LICENSE
mail_alias_creator-1.2.2.dist-info/METADATA
mail_alias_creator-1.2.2.dist-info/WHEEL
mail_alias_creator-1.2.2.dist-info/entry_points.txt
mail_alias_creator-1.2.2.dist-info/RECORD
