Metadata-Version: 2.1
Name: mail_alias_creator
Version: 1.2.2
Summary: Set of python scripts to create our mail alias tables from alias definitions
Home-page: https://github.com/stuvusIT/mail_alias_creator
License: MIT
Author: Tim Neumann
Author-email: neumantm@fius.informatik.uni-stuttgart.de
Requires-Python: >=3.6,<4.0
Classifier: License :: OSI Approved :: MIT License
Classifier: Programming Language :: Python :: 3
Classifier: Programming Language :: Python :: 3.6
Classifier: Programming Language :: Python :: 3.7
Classifier: Programming Language :: Python :: 3.8
Classifier: Programming Language :: Python :: 3.9
Classifier: Programming Language :: Python :: 3.10
Classifier: Programming Language :: Python :: 3.11
Classifier: Programming Language :: Python :: 3.12
Requires-Dist: ldap3 (>=2.7,<3.0)
Requires-Dist: pyyaml (>=6.0,<7.0)
Project-URL: Repository, https://github.com/stuvusIT/mail_alias_creator
